[{"slug": "pcox-quadro-2-11", "label": "Totale generale delle Entrate", "values": [{"2016": {"abs": 6226275.74, "pc": 1550.75360896638}}, {"2017": {"abs": 0.0, "pc": 0.0}}, {"2018": {"abs": 0.0, "pc": 0.0}}], "children": []}, {"slug": "pcox-quadro-2-2", "label": "Entrate correnti di natura tributaria, contributiva e perequativa", "values": [{"2016": {"abs": 4178760.04, "pc": 1040.78705853051}}, {"2017": {"abs": 0.0, "pc": 0.0}}, {"2018": {"abs": 0.0, "pc": 0.0}}], "children": [{"slug": "pcox-quadro-2-2-10", "label": "Imposte,tasse e proventi assimilati", "values": [{"2016": {"abs": 2986510.86, "pc": 743.838321295143}}, {"2017": {"abs": 0.0, "pc": 0.0}}, {"2018": {"abs": 0.0, "pc": 0.0}}]}, {"slug": "pcox-quadro-2-2-12", "label": "Compartecipazioni di tributi", "values": [{"2016": {"abs": 0.0, "pc": 0.0}}, {"2017": {"abs": 0.0, "pc": 0.0}}, {"2018": {"abs": 0.0, "pc": 0.0}}]}, {"slug": "pcox-quadro-2-2-14", "label": "Fondi perequativi  da Amministrazioni Centrali", "values": [{"2016": {"abs": 1192249.18, "pc": 296.948737235367}}, {"2017": {"abs": 0.0, "pc": 0.0}}, {"2018": {"abs": 0.0, "pc": 0.0}}]}, {"slug": "pcox-quadro-2-2-16", "label": "Fondi perequativi  dalla Regione o Provincia autonoma", "values": [{"2016": {"abs": 0.0, "pc": 0.0}}, {"2017": {"abs": 0.0, "pc": 0.0}}, {"2018": {"abs": 0.0, "pc": 0.0}}]}]}, {"slug": "pcox-quadro-2-3", "label": "Trasferimenti correnti", "values": [{"2016": {"abs": 139746.64, "pc": 34.8061369863014}}, {"2017": {"abs": 0.0, "pc": 0.0}}, {"2018": {"abs": 0.0, "pc": 0.0}}], "children": [{"slug": "pcox-quadro-2-3-20", "label": "Trasferimenti correnti da Amministrazioni pubbliche -", "values": [{"2016": {"abs": 139746.64, "pc": 34.8061369863014}}, {"2017": {"abs": 0.0, "pc": 0.0}}, {"2018": {"abs": 0.0, "pc": 0.0}}]}, {"slug": "pcox-quadro-2-3-22", "label": "Trasferimenti correnti da Famiglie", "values": [{"2016": {"abs": 0.0, "pc": 0.0}}, {"2017": {"abs": 0.0, "pc": 0.0}}, {"2018": {"abs": 0.0, "pc": 0.0}}]}, {"slug": "pcox-quadro-2-3-24", "label": "Trasferimenti correnti da Imprese", "values": [{"2016": {"abs": 0.0, "pc": 0.0}}, {"2017": {"abs": 0.0, "pc": 0.0}}, {"2018": {"abs": 0.0, "pc": 0.0}}]}, {"slug": "pcox-quadro-2-3-26", "label": "Trasferimenti correnti da Istituzioni Sociali Private", "values": [{"2016": {"abs": 0.0, "pc": 0.0}}, {"2017": {"abs": 0.0, "pc": 0.0}}, {"2018": {"abs": 0.0, "pc": 0.0}}]}, {"slug": "pcox-quadro-2-3-28", "label": "Trasferimenti correnti dall'Unione europea e dal Resto del Mondo- previsione di cassa", "values": [{"2016": {"abs": 0.0, "pc": 0.0}}, {"2017": {"abs": 0.0, "pc": 0.0}}, {"2018": {"abs": 0.0, "pc": 0.0}}]}]}, {"slug": "pcox-quadro-2-4", "label": "Entrate extratributarie", "values": [{"2016": {"abs": 363028.89, "pc": 90.4181544209216}}, {"2017": {"abs": 0.0, "pc": 0.0}}, {"2018": {"abs": 0.0, "pc": 0.0}}], "children": [{"slug": "pcox-quadro-2-4-32", "label": "Vendita di beni e servizi e proventi derivanti dalla gestione dei beni", "values": [{"2016": {"abs": 207939.01, "pc": 51.7905379825654}}, {"2017": {"abs": 0.0, "pc": 0.0}}, {"2018": {"abs": 0.0, "pc": 0.0}}]}, {"slug": "pcox-quadro-2-4-34", "label": "Proventi derivanti dall'attivit\u00e0 di controllo e repressione delle irregolarit\u00e0 e degli illeciti", "values": [{"2016": {"abs": 0.0, "pc": 0.0}}, {"2017": {"abs": 0.0, "pc": 0.0}}, {"2018": {"abs": 0.0, "pc": 0.0}}]}, {"slug": "pcox-quadro-2-4-36", "label": "Interessi attivi", "values": [{"2016": {"abs": 2407.54, "pc": 0.599636363636364}}, {"2017": {"abs": 0.0, "pc": 0.0}}, {"2018": {"abs": 0.0, "pc": 0.0}}]}, {"slug": "pcox-quadro-2-4-38", "label": "Altre entrate da redditi da capitale", "values": [{"2016": {"abs": 0.0, "pc": 0.0}}, {"2017": {"abs": 0.0, "pc": 0.0}}, {"2018": {"abs": 0.0, "pc": 0.0}}]}, {"slug": "pcox-quadro-2-4-40", "label": "Rimborsi e altre entrate correnti", "values": [{"2016": {"abs": 152682.34, "pc": 38.0279800747198}}, {"2017": {"abs": 0.0, "pc": 0.0}}, {"2018": {"abs": 0.0, "pc": 0.0}}]}]}, {"slug": "pcox-quadro-2-5", "label": "Entrate in conto capitale", "values": [{"2016": {"abs": 230074.86, "pc": 57.3038256537983}}, {"2017": {"abs": 0.0, "pc": 0.0}}, {"2018": {"abs": 0.0, "pc": 0.0}}], "children": [{"slug": "pcox-quadro-2-5-44", "label": "Tributi in conto capitale", "values": [{"2016": {"abs": 0.0, "pc": 0.0}}, {"2017": {"abs": 0.0, "pc": 0.0}}, {"2018": {"abs": 0.0, "pc": 0.0}}]}, {"slug": "pcox-quadro-2-5-46", "label": "Contributi agli investimenti", "values": [{"2016": {"abs": 159318.0, "pc": 39.680697384807}}, {"2017": {"abs": 0.0, "pc": 0.0}}, {"2018": {"abs": 0.0, "pc": 0.0}}]}, {"slug": "pcox-quadro-2-5-48", "label": "Altri trasferimenti in conto capitale", "values": [{"2016": {"abs": 3469.23, "pc": 0.864067247820672}}, {"2017": {"abs": 0.0, "pc": 0.0}}, {"2018": {"abs": 0.0, "pc": 0.0}}]}, {"slug": "pcox-quadro-2-5-50", "label": "Entrate da alienazione di beni materiali e immateriali", "values": [{"2016": {"abs": 17287.63, "pc": 4.30576089663761}}, {"2017": {"abs": 0.0, "pc": 0.0}}, {"2018": {"abs": 0.0, "pc": 0.0}}]}, {"slug": "pcox-quadro-2-5-52", "label": "Altre entrate in conto capitale", "values": [{"2016": {"abs": 50000.0, "pc": 12.453300124533}}, {"2017": {"abs": 0.0, "pc": 0.0}}, {"2018": {"abs": 0.0, "pc": 0.0}}]}]}, {"slug": "pcox-quadro-2-6", "label": "Entrate da riduzione di attivita\u0300 finanziarie", "values": [{"2016": {"abs": 0.0, "pc": 0.0}}, {"2017": {"abs": 0.0, "pc": 0.0}}, {"2018": {"abs": 0.0, "pc": 0.0}}], "children": [{"slug": "pcox-quadro-2-6-56", "label": "Alienazione di attivit\u00e0 finanziarie", "values": [{"2016": {"abs": 0.0, "pc": 0.0}}, {"2017": {"abs": 0.0, "pc": 0.0}}, {"2018": {"abs": 0.0, "pc": 0.0}}]}, {"slug": "pcox-quadro-2-6-58", "label": "Riscossione crediti di breve termine", "values": [{"2016": {"abs": 0.0, "pc": 0.0}}, {"2017": {"abs": 0.0, "pc": 0.0}}, {"2018": {"abs": 0.0, "pc": 0.0}}]}, {"slug": "pcox-quadro-2-6-60", "label": "Riscossione crediti di medio", "values": [{"2016": {"abs": 0.0, "pc": 0.0}}, {"2017": {"abs": 0.0, "pc": 0.0}}, {"2018": {"abs": 0.0, "pc": 0.0}}]}, {"slug": "pcox-quadro-2-6-62", "label": "Altre entrate per riduzione di attivit\u00e0 finanziarie", "values": [{"2016": {"abs": 0.0, "pc": 0.0}}, {"2017": {"abs": 0.0, "pc": 0.0}}, {"2018": {"abs": 0.0, "pc": 0.0}}]}]}, {"slug": "pcox-quadro-2-7", "label": "Accensione prestiti", "values": [{"2016": {"abs": 86167.63, "pc": 21.4614271481943}}, {"2017": {"abs": 0.0, "pc": 0.0}}, {"2018": {"abs": 0.0, "pc": 0.0}}], "children": [{"slug": "pcox-quadro-2-7-66", "label": "Emissione di titoli obbligazionari", "values": [{"2016": {"abs": 0.0, "pc": 0.0}}, {"2017": {"abs": 0.0, "pc": 0.0}}, {"2018": {"abs": 0.0, "pc": 0.0}}]}, {"slug": "pcox-quadro-2-7-68", "label": "Accensione prestiti a breve termine", "values": [{"2016": {"abs": 0.0, "pc": 0.0}}, {"2017": {"abs": 0.0, "pc": 0.0}}, {"2018": {"abs": 0.0, "pc": 0.0}}]}, {"slug": "pcox-quadro-2-7-70", "label": "Accensione mutui e altri finanziamenti a medio lungo termine", "values": [{"2016": {"abs": 86167.63, "pc": 21.4614271481943}}, {"2017": {"abs": 0.0, "pc": 0.0}}, {"2018": {"abs": 0.0, "pc": 0.0}}]}, {"slug": "pcox-quadro-2-7-72", "label": "Altre forme di indebitamento", "values": [{"2016": {"abs": 0.0, "pc": 0.0}}, {"2017": {"abs": 0.0, "pc": 0.0}}, {"2018": {"abs": 0.0, "pc": 0.0}}]}]}, {"slug": "pcox-quadro-2-8", "label": "Anticipazioni da istituto tesoriere/cassiere", "values": [{"2016": {"abs": 300000.0, "pc": 74.719800747198}}, {"2017": {"abs": 0.0, "pc": 0.0}}, {"2018": {"abs": 0.0, "pc": 0.0}}], "children": [{"slug": "pcox-quadro-2-8-76", "label": "Anticipazione da istituto tesoriere/cassiere", "values": [{"2016": {"abs": 300000.0, "pc": 74.719800747198}}, {"2017": {"abs": 0.0, "pc": 0.0}}, {"2018": {"abs": 0.0, "pc": 0.0}}]}]}, {"slug": "pcox-quadro-2-9", "label": "Entrate per conto terzi e partite di giro", "values": [{"2016": {"abs": 928497.68, "pc": 231.257205479452}}, {"2017": {"abs": 0.0, "pc": 0.0}}, {"2018": {"abs": 0.0, "pc": 0.0}}], "children": [{"slug": "pcox-quadro-2-9-80", "label": "Entrate per partite di giro", "values": [{"2016": {"abs": 320118.49, "pc": 79.7306326276463}}, {"2017": {"abs": 0.0, "pc": 0.0}}, {"2018": {"abs": 0.0, "pc": 0.0}}]}, {"slug": "pcox-quadro-2-9-82", "label": "Entrate per conto terzi", "values": [{"2016": {"abs": 608379.19, "pc": 151.526572851806}}, {"2017": {"abs": 0.0, "pc": 0.0}}, {"2018": {"abs": 0.0, "pc": 0.0}}]}]}]