[{"slug": "pcox-quadro-2-11", "label": "Totale generale delle Entrate", "values": [{"2016": {"abs": 24806546.26, "pc": 5002.32834442428}}, {"2017": {"abs": 0.0, "pc": 0.0}}, {"2018": {"abs": 0.0, "pc": 0.0}}], "children": []}, {"slug": "pcox-quadro-2-2", "label": "Entrate correnti di natura tributaria, contributiva e perequativa", "values": [{"2016": {"abs": 2707418.55, "pc": 545.960586811857}}, {"2017": {"abs": 0.0, "pc": 0.0}}, {"2018": {"abs": 0.0, "pc": 0.0}}], "children": [{"slug": "pcox-quadro-2-2-10", "label": "Imposte,tasse e proventi assimilati", "values": [{"2016": {"abs": 2283995.28, "pc": 460.575777374471}}, {"2017": {"abs": 0.0, "pc": 0.0}}, {"2018": {"abs": 0.0, "pc": 0.0}}]}, {"slug": "pcox-quadro-2-2-12", "label": "Compartecipazioni di tributi", "values": [{"2016": {"abs": 100.0, "pc": 0.020165355918532}}, {"2017": {"abs": 0.0, "pc": 0.0}}, {"2018": {"abs": 0.0, "pc": 0.0}}]}, {"slug": "pcox-quadro-2-2-14", "label": "Fondi perequativi  da Amministrazioni Centrali", "values": [{"2016": {"abs": 423323.27, "pc": 85.364644081468}}, {"2017": {"abs": 0.0, "pc": 0.0}}, {"2018": {"abs": 0.0, "pc": 0.0}}]}, {"slug": "pcox-quadro-2-2-16", "label": "Fondi perequativi  dalla Regione o Provincia autonoma", "values": [{"2016": {"abs": 0.0, "pc": 0.0}}, {"2017": {"abs": 0.0, "pc": 0.0}}, {"2018": {"abs": 0.0, "pc": 0.0}}]}]}, {"slug": "pcox-quadro-2-3", "label": "Trasferimenti correnti", "values": [{"2016": {"abs": 501828.74, "pc": 101.195551522484}}, {"2017": {"abs": 0.0, "pc": 0.0}}, {"2018": {"abs": 0.0, "pc": 0.0}}], "children": [{"slug": "pcox-quadro-2-3-20", "label": "Trasferimenti correnti da Amministrazioni pubbliche -", "values": [{"2016": {"abs": 482328.74, "pc": 97.2633071183706}}, {"2017": {"abs": 0.0, "pc": 0.0}}, {"2018": {"abs": 0.0, "pc": 0.0}}]}, {"slug": "pcox-quadro-2-3-22", "label": "Trasferimenti correnti da Famiglie", "values": [{"2016": {"abs": 0.0, "pc": 0.0}}, {"2017": {"abs": 0.0, "pc": 0.0}}, {"2018": {"abs": 0.0, "pc": 0.0}}]}, {"slug": "pcox-quadro-2-3-24", "label": "Trasferimenti correnti da Imprese", "values": [{"2016": {"abs": 19500.0, "pc": 3.93224440411373}}, {"2017": {"abs": 0.0, "pc": 0.0}}, {"2018": {"abs": 0.0, "pc": 0.0}}]}, {"slug": "pcox-quadro-2-3-26", "label": "Trasferimenti correnti da Istituzioni Sociali Private", "values": [{"2016": {"abs": 0.0, "pc": 0.0}}, {"2017": {"abs": 0.0, "pc": 0.0}}, {"2018": {"abs": 0.0, "pc": 0.0}}]}, {"slug": "pcox-quadro-2-3-28", "label": "Trasferimenti correnti dall'Unione europea e dal Resto del Mondo- previsione di cassa", "values": [{"2016": {"abs": 0.0, "pc": 0.0}}, {"2017": {"abs": 0.0, "pc": 0.0}}, {"2018": {"abs": 0.0, "pc": 0.0}}]}]}, {"slug": "pcox-quadro-2-4", "label": "Entrate extratributarie", "values": [{"2016": {"abs": 7256659.25, "pc": 1463.33116555757}}, {"2017": {"abs": 0.0, "pc": 0.0}}, {"2018": {"abs": 0.0, "pc": 0.0}}], "children": [{"slug": "pcox-quadro-2-4-32", "label": "Vendita di beni e servizi e proventi derivanti dalla gestione dei beni", "values": [{"2016": {"abs": 6149522.47, "pc": 1240.0730933656}}, {"2017": {"abs": 0.0, "pc": 0.0}}, {"2018": {"abs": 0.0, "pc": 0.0}}]}, {"slug": "pcox-quadro-2-4-34", "label": "Proventi derivanti dall'attivit\u00e0 di controllo e repressione delle irregolarit\u00e0 e degli illeciti", "values": [{"2016": {"abs": 1180.0, "pc": 0.237951199838677}}, {"2017": {"abs": 0.0, "pc": 0.0}}, {"2018": {"abs": 0.0, "pc": 0.0}}]}, {"slug": "pcox-quadro-2-4-36", "label": "Interessi attivi", "values": [{"2016": {"abs": 248509.33, "pc": 50.1127908852591}}, {"2017": {"abs": 0.0, "pc": 0.0}}, {"2018": {"abs": 0.0, "pc": 0.0}}]}, {"slug": "pcox-quadro-2-4-38", "label": "Altre entrate da redditi da capitale", "values": [{"2016": {"abs": 179400.0, "pc": 36.1766485178463}}, {"2017": {"abs": 0.0, "pc": 0.0}}, {"2018": {"abs": 0.0, "pc": 0.0}}]}, {"slug": "pcox-quadro-2-4-40", "label": "Rimborsi e altre entrate correnti", "values": [{"2016": {"abs": 678047.45, "pc": 136.73068158903}}, {"2017": {"abs": 0.0, "pc": 0.0}}, {"2018": {"abs": 0.0, "pc": 0.0}}]}]}, {"slug": "pcox-quadro-2-5", "label": "Entrate in conto capitale", "values": [{"2016": {"abs": 1387968.84, "pc": 279.888856624319}}, {"2017": {"abs": 0.0, "pc": 0.0}}, {"2018": {"abs": 0.0, "pc": 0.0}}], "children": [{"slug": "pcox-quadro-2-5-44", "label": "Tributi in conto capitale", "values": [{"2016": {"abs": 4883.44, "pc": 0.984763057067957}}, {"2017": {"abs": 0.0, "pc": 0.0}}, {"2018": {"abs": 0.0, "pc": 0.0}}]}, {"slug": "pcox-quadro-2-5-46", "label": "Contributi agli investimenti", "values": [{"2016": {"abs": 118680.58, "pc": 23.9323613631781}}, {"2017": {"abs": 0.0, "pc": 0.0}}, {"2018": {"abs": 0.0, "pc": 0.0}}]}, {"slug": "pcox-quadro-2-5-48", "label": "Altri trasferimenti in conto capitale", "values": [{"2016": {"abs": 1163771.98, "pc": 234.678761847147}}, {"2017": {"abs": 0.0, "pc": 0.0}}, {"2018": {"abs": 0.0, "pc": 0.0}}]}, {"slug": "pcox-quadro-2-5-50", "label": "Entrate da alienazione di beni materiali e immateriali", "values": [{"2016": {"abs": 19335.0, "pc": 3.89897156684816}}, {"2017": {"abs": 0.0, "pc": 0.0}}, {"2018": {"abs": 0.0, "pc": 0.0}}]}, {"slug": "pcox-quadro-2-5-52", "label": "Altre entrate in conto capitale", "values": [{"2016": {"abs": 81297.84, "pc": 16.3939987900786}}, {"2017": {"abs": 0.0, "pc": 0.0}}, {"2018": {"abs": 0.0, "pc": 0.0}}]}]}, {"slug": "pcox-quadro-2-6", "label": "Entrate da riduzione di attivita\u0300 finanziarie", "values": [{"2016": {"abs": 8622733.74, "pc": 1738.80494857834}}, {"2017": {"abs": 0.0, "pc": 0.0}}, {"2018": {"abs": 0.0, "pc": 0.0}}], "children": [{"slug": "pcox-quadro-2-6-56", "label": "Alienazione di attivit\u00e0 finanziarie", "values": [{"2016": {"abs": 5617548.0, "pc": 1132.79854809437}}, {"2017": {"abs": 0.0, "pc": 0.0}}, {"2018": {"abs": 0.0, "pc": 0.0}}]}, {"slug": "pcox-quadro-2-6-58", "label": "Riscossione crediti di breve termine", "values": [{"2016": {"abs": 0.0, "pc": 0.0}}, {"2017": {"abs": 0.0, "pc": 0.0}}, {"2018": {"abs": 0.0, "pc": 0.0}}]}, {"slug": "pcox-quadro-2-6-60", "label": "Riscossione crediti di medio", "values": [{"2016": {"abs": 3005185.74, "pc": 606.006400483969}}, {"2017": {"abs": 0.0, "pc": 0.0}}, {"2018": {"abs": 0.0, "pc": 0.0}}]}, {"slug": "pcox-quadro-2-6-62", "label": "Altre entrate per riduzione di attivit\u00e0 finanziarie", "values": [{"2016": {"abs": 0.0, "pc": 0.0}}, {"2017": {"abs": 0.0, "pc": 0.0}}, {"2018": {"abs": 0.0, "pc": 0.0}}]}]}, {"slug": "pcox-quadro-2-7", "label": "Accensione prestiti", "values": [{"2016": {"abs": 523752.59, "pc": 105.616573906029}}, {"2017": {"abs": 0.0, "pc": 0.0}}, {"2018": {"abs": 0.0, "pc": 0.0}}], "children": [{"slug": "pcox-quadro-2-7-66", "label": "Emissione di titoli obbligazionari", "values": [{"2016": {"abs": 0.0, "pc": 0.0}}, {"2017": {"abs": 0.0, "pc": 0.0}}, {"2018": {"abs": 0.0, "pc": 0.0}}]}, {"slug": "pcox-quadro-2-7-68", "label": "Accensione prestiti a breve termine", "values": [{"2016": {"abs": 0.0, "pc": 0.0}}, {"2017": {"abs": 0.0, "pc": 0.0}}, {"2018": {"abs": 0.0, "pc": 0.0}}]}, {"slug": "pcox-quadro-2-7-70", "label": "Accensione mutui e altri finanziamenti a medio lungo termine", "values": [{"2016": {"abs": 523752.59, "pc": 105.616573906029}}, {"2017": {"abs": 0.0, "pc": 0.0}}, {"2018": {"abs": 0.0, "pc": 0.0}}]}, {"slug": "pcox-quadro-2-7-72", "label": "Altre forme di indebitamento", "values": [{"2016": {"abs": 0.0, "pc": 0.0}}, {"2017": {"abs": 0.0, "pc": 0.0}}, {"2018": {"abs": 0.0, "pc": 0.0}}]}]}, {"slug": "pcox-quadro-2-8", "label": "Anticipazioni da istituto tesoriere/cassiere", "values": [{"2016": {"abs": 1860950.18, "pc": 375.267227263561}}, {"2017": {"abs": 0.0, "pc": 0.0}}, {"2018": {"abs": 0.0, "pc": 0.0}}], "children": [{"slug": "pcox-quadro-2-8-76", "label": "Anticipazione da istituto tesoriere/cassiere", "values": [{"2016": {"abs": 1860950.18, "pc": 375.267227263561}}, {"2017": {"abs": 0.0, "pc": 0.0}}, {"2018": {"abs": 0.0, "pc": 0.0}}]}]}, {"slug": "pcox-quadro-2-9", "label": "Entrate per conto terzi e partite di giro", "values": [{"2016": {"abs": 1945234.37, "pc": 392.263434160113}}, {"2017": {"abs": 0.0, "pc": 0.0}}, {"2018": {"abs": 0.0, "pc": 0.0}}], "children": [{"slug": "pcox-quadro-2-9-80", "label": "Entrate per partite di giro", "values": [{"2016": {"abs": 1424729.48, "pc": 287.30177051825}}, {"2017": {"abs": 0.0, "pc": 0.0}}, {"2018": {"abs": 0.0, "pc": 0.0}}]}, {"slug": "pcox-quadro-2-9-82", "label": "Entrate per conto terzi", "values": [{"2016": {"abs": 520504.89, "pc": 104.961663641863}}, {"2017": {"abs": 0.0, "pc": 0.0}}, {"2018": {"abs": 0.0, "pc": 0.0}}]}]}]