[{"slug": "pcox-quadro-2-11", "label": "Totale generale delle Entrate", "values": [{"2016": {"abs": 7103143.62, "pc": 900.271688212928}}, {"2017": {"abs": 0.0, "pc": 0.0}}, {"2018": {"abs": 0.0, "pc": 0.0}}], "children": []}, {"slug": "pcox-quadro-2-2", "label": "Entrate correnti di natura tributaria, contributiva e perequativa", "values": [{"2016": {"abs": 3090457.57, "pc": 391.692974651458}}, {"2017": {"abs": 0.0, "pc": 0.0}}, {"2018": {"abs": 0.0, "pc": 0.0}}], "children": [{"slug": "pcox-quadro-2-2-10", "label": "Imposte,tasse e proventi assimilati", "values": [{"2016": {"abs": 3090457.57, "pc": 391.692974651458}}, {"2017": {"abs": 0.0, "pc": 0.0}}, {"2018": {"abs": 0.0, "pc": 0.0}}]}, {"slug": "pcox-quadro-2-2-12", "label": "Compartecipazioni di tributi", "values": [{"2016": {"abs": 0.0, "pc": 0.0}}, {"2017": {"abs": 0.0, "pc": 0.0}}, {"2018": {"abs": 0.0, "pc": 0.0}}]}, {"slug": "pcox-quadro-2-2-14", "label": "Fondi perequativi  da Amministrazioni Centrali", "values": [{"2016": {"abs": 0.0, "pc": 0.0}}, {"2017": {"abs": 0.0, "pc": 0.0}}, {"2018": {"abs": 0.0, "pc": 0.0}}]}, {"slug": "pcox-quadro-2-2-16", "label": "Fondi perequativi  dalla Regione o Provincia autonoma", "values": [{"2016": {"abs": 0.0, "pc": 0.0}}, {"2017": {"abs": 0.0, "pc": 0.0}}, {"2018": {"abs": 0.0, "pc": 0.0}}]}]}, {"slug": "pcox-quadro-2-3", "label": "Trasferimenti correnti", "values": [{"2016": {"abs": 1046559.75, "pc": 132.643821292776}}, {"2017": {"abs": 0.0, "pc": 0.0}}, {"2018": {"abs": 0.0, "pc": 0.0}}], "children": [{"slug": "pcox-quadro-2-3-20", "label": "Trasferimenti correnti da Amministrazioni pubbliche -", "values": [{"2016": {"abs": 1046559.75, "pc": 132.643821292776}}, {"2017": {"abs": 0.0, "pc": 0.0}}, {"2018": {"abs": 0.0, "pc": 0.0}}]}, {"slug": "pcox-quadro-2-3-22", "label": "Trasferimenti correnti da Famiglie", "values": [{"2016": {"abs": 0.0, "pc": 0.0}}, {"2017": {"abs": 0.0, "pc": 0.0}}, {"2018": {"abs": 0.0, "pc": 0.0}}]}, {"slug": "pcox-quadro-2-3-24", "label": "Trasferimenti correnti da Imprese", "values": [{"2016": {"abs": 0.0, "pc": 0.0}}, {"2017": {"abs": 0.0, "pc": 0.0}}, {"2018": {"abs": 0.0, "pc": 0.0}}]}, {"slug": "pcox-quadro-2-3-26", "label": "Trasferimenti correnti da Istituzioni Sociali Private", "values": [{"2016": {"abs": 0.0, "pc": 0.0}}, {"2017": {"abs": 0.0, "pc": 0.0}}, {"2018": {"abs": 0.0, "pc": 0.0}}]}, {"slug": "pcox-quadro-2-3-28", "label": "Trasferimenti correnti dall'Unione europea e dal Resto del Mondo- previsione di cassa", "values": [{"2016": {"abs": 0.0, "pc": 0.0}}, {"2017": {"abs": 0.0, "pc": 0.0}}, {"2018": {"abs": 0.0, "pc": 0.0}}]}]}, {"slug": "pcox-quadro-2-4", "label": "Entrate extratributarie", "values": [{"2016": {"abs": 1283113.14, "pc": 162.625239543726}}, {"2017": {"abs": 0.0, "pc": 0.0}}, {"2018": {"abs": 0.0, "pc": 0.0}}], "children": [{"slug": "pcox-quadro-2-4-32", "label": "Vendita di beni e servizi e proventi derivanti dalla gestione dei beni", "values": [{"2016": {"abs": 556540.94, "pc": 70.5375082382763}}, {"2017": {"abs": 0.0, "pc": 0.0}}, {"2018": {"abs": 0.0, "pc": 0.0}}]}, {"slug": "pcox-quadro-2-4-34", "label": "Proventi derivanti dall'attivit\u00e0 di controllo e repressione delle irregolarit\u00e0 e degli illeciti", "values": [{"2016": {"abs": 448833.35, "pc": 56.8863561470215}}, {"2017": {"abs": 0.0, "pc": 0.0}}, {"2018": {"abs": 0.0, "pc": 0.0}}]}, {"slug": "pcox-quadro-2-4-36", "label": "Interessi attivi", "values": [{"2016": {"abs": 694.98, "pc": 0.0880836501901141}}, {"2017": {"abs": 0.0, "pc": 0.0}}, {"2018": {"abs": 0.0, "pc": 0.0}}]}, {"slug": "pcox-quadro-2-4-38", "label": "Altre entrate da redditi da capitale", "values": [{"2016": {"abs": 75000.0, "pc": 9.50570342205323}}, {"2017": {"abs": 0.0, "pc": 0.0}}, {"2018": {"abs": 0.0, "pc": 0.0}}]}, {"slug": "pcox-quadro-2-4-40", "label": "Rimborsi e altre entrate correnti", "values": [{"2016": {"abs": 202043.87, "pc": 25.607588086185}}, {"2017": {"abs": 0.0, "pc": 0.0}}, {"2018": {"abs": 0.0, "pc": 0.0}}]}]}, {"slug": "pcox-quadro-2-5", "label": "Entrate in conto capitale", "values": [{"2016": {"abs": 583163.33, "pc": 73.9117021546261}}, {"2017": {"abs": 0.0, "pc": 0.0}}, {"2018": {"abs": 0.0, "pc": 0.0}}], "children": [{"slug": "pcox-quadro-2-5-44", "label": "Tributi in conto capitale", "values": [{"2016": {"abs": 0.0, "pc": 0.0}}, {"2017": {"abs": 0.0, "pc": 0.0}}, {"2018": {"abs": 0.0, "pc": 0.0}}]}, {"slug": "pcox-quadro-2-5-46", "label": "Contributi agli investimenti", "values": [{"2016": {"abs": 209633.4, "pc": 26.5695057034221}}, {"2017": {"abs": 0.0, "pc": 0.0}}, {"2018": {"abs": 0.0, "pc": 0.0}}]}, {"slug": "pcox-quadro-2-5-48", "label": "Altri trasferimenti in conto capitale", "values": [{"2016": {"abs": 0.0, "pc": 0.0}}, {"2017": {"abs": 0.0, "pc": 0.0}}, {"2018": {"abs": 0.0, "pc": 0.0}}]}, {"slug": "pcox-quadro-2-5-50", "label": "Entrate da alienazione di beni materiali e immateriali", "values": [{"2016": {"abs": 250000.0, "pc": 31.6856780735108}}, {"2017": {"abs": 0.0, "pc": 0.0}}, {"2018": {"abs": 0.0, "pc": 0.0}}]}, {"slug": "pcox-quadro-2-5-52", "label": "Altre entrate in conto capitale", "values": [{"2016": {"abs": 123529.93, "pc": 15.6565183776933}}, {"2017": {"abs": 0.0, "pc": 0.0}}, {"2018": {"abs": 0.0, "pc": 0.0}}]}]}, {"slug": "pcox-quadro-2-6", "label": "Entrate da riduzione di attivita\u0300 finanziarie", "values": [{"2016": {"abs": 0.0, "pc": 0.0}}, {"2017": {"abs": 0.0, "pc": 0.0}}, {"2018": {"abs": 0.0, "pc": 0.0}}], "children": [{"slug": "pcox-quadro-2-6-56", "label": "Alienazione di attivit\u00e0 finanziarie", "values": [{"2016": {"abs": 0.0, "pc": 0.0}}, {"2017": {"abs": 0.0, "pc": 0.0}}, {"2018": {"abs": 0.0, "pc": 0.0}}]}, {"slug": "pcox-quadro-2-6-58", "label": "Riscossione crediti di breve termine", "values": [{"2016": {"abs": 0.0, "pc": 0.0}}, {"2017": {"abs": 0.0, "pc": 0.0}}, {"2018": {"abs": 0.0, "pc": 0.0}}]}, {"slug": "pcox-quadro-2-6-60", "label": "Riscossione crediti di medio", "values": [{"2016": {"abs": 0.0, "pc": 0.0}}, {"2017": {"abs": 0.0, "pc": 0.0}}, {"2018": {"abs": 0.0, "pc": 0.0}}]}, {"slug": "pcox-quadro-2-6-62", "label": "Altre entrate per riduzione di attivit\u00e0 finanziarie", "values": [{"2016": {"abs": 0.0, "pc": 0.0}}, {"2017": {"abs": 0.0, "pc": 0.0}}, {"2018": {"abs": 0.0, "pc": 0.0}}]}]}, {"slug": "pcox-quadro-2-7", "label": "Accensione prestiti", "values": [{"2016": {"abs": 0.0, "pc": 0.0}}, {"2017": {"abs": 0.0, "pc": 0.0}}, {"2018": {"abs": 0.0, "pc": 0.0}}], "children": [{"slug": "pcox-quadro-2-7-66", "label": "Emissione di titoli obbligazionari", "values": [{"2016": {"abs": 0.0, "pc": 0.0}}, {"2017": {"abs": 0.0, "pc": 0.0}}, {"2018": {"abs": 0.0, "pc": 0.0}}]}, {"slug": "pcox-quadro-2-7-68", "label": "Accensione prestiti a breve termine", "values": [{"2016": {"abs": 0.0, "pc": 0.0}}, {"2017": {"abs": 0.0, "pc": 0.0}}, {"2018": {"abs": 0.0, "pc": 0.0}}]}, {"slug": "pcox-quadro-2-7-70", "label": "Accensione mutui e altri finanziamenti a medio lungo termine", "values": [{"2016": {"abs": 0.0, "pc": 0.0}}, {"2017": {"abs": 0.0, "pc": 0.0}}, {"2018": {"abs": 0.0, "pc": 0.0}}]}, {"slug": "pcox-quadro-2-7-72", "label": "Altre forme di indebitamento", "values": [{"2016": {"abs": 0.0, "pc": 0.0}}, {"2017": {"abs": 0.0, "pc": 0.0}}, {"2018": {"abs": 0.0, "pc": 0.0}}]}]}, {"slug": "pcox-quadro-2-8", "label": "Anticipazioni da istituto tesoriere/cassiere", "values": [{"2016": {"abs": 0.0, "pc": 0.0}}, {"2017": {"abs": 0.0, "pc": 0.0}}, {"2018": {"abs": 0.0, "pc": 0.0}}], "children": [{"slug": "pcox-quadro-2-8-76", "label": "Anticipazione da istituto tesoriere/cassiere", "values": [{"2016": {"abs": 0.0, "pc": 0.0}}, {"2017": {"abs": 0.0, "pc": 0.0}}, {"2018": {"abs": 0.0, "pc": 0.0}}]}]}, {"slug": "pcox-quadro-2-9", "label": "Entrate per conto terzi e partite di giro", "values": [{"2016": {"abs": 1099849.83, "pc": 139.397950570342}}, {"2017": {"abs": 0.0, "pc": 0.0}}, {"2018": {"abs": 0.0, "pc": 0.0}}], "children": [{"slug": "pcox-quadro-2-9-80", "label": "Entrate per partite di giro", "values": [{"2016": {"abs": 891300.0, "pc": 112.965779467681}}, {"2017": {"abs": 0.0, "pc": 0.0}}, {"2018": {"abs": 0.0, "pc": 0.0}}]}, {"slug": "pcox-quadro-2-9-82", "label": "Entrate per conto terzi", "values": [{"2016": {"abs": 208549.83, "pc": 26.4321711026616}}, {"2017": {"abs": 0.0, "pc": 0.0}}, {"2018": {"abs": 0.0, "pc": 0.0}}]}]}]