[{"slug": "pcox-quadro-2-11", "label": "Totale generale delle Entrate", "values": [{"2016": {"abs": 9489963.19, "pc": 3005.05484167194}}, {"2017": {"abs": 0.0, "pc": 0.0}}, {"2018": {"abs": 0.0, "pc": 0.0}}], "children": []}, {"slug": "pcox-quadro-2-2", "label": "Entrate correnti di natura tributaria, contributiva e perequativa", "values": [{"2016": {"abs": 2625553.28, "pc": 831.397492083597}}, {"2017": {"abs": 0.0, "pc": 0.0}}, {"2018": {"abs": 0.0, "pc": 0.0}}], "children": [{"slug": "pcox-quadro-2-2-10", "label": "Imposte,tasse e proventi assimilati", "values": [{"2016": {"abs": 2625553.28, "pc": 831.397492083597}}, {"2017": {"abs": 0.0, "pc": 0.0}}, {"2018": {"abs": 0.0, "pc": 0.0}}]}, {"slug": "pcox-quadro-2-2-12", "label": "Compartecipazioni di tributi", "values": [{"2016": {"abs": 0.0, "pc": 0.0}}, {"2017": {"abs": 0.0, "pc": 0.0}}, {"2018": {"abs": 0.0, "pc": 0.0}}]}, {"slug": "pcox-quadro-2-2-14", "label": "Fondi perequativi  da Amministrazioni Centrali", "values": [{"2016": {"abs": 0.0, "pc": 0.0}}, {"2017": {"abs": 0.0, "pc": 0.0}}, {"2018": {"abs": 0.0, "pc": 0.0}}]}, {"slug": "pcox-quadro-2-2-16", "label": "Fondi perequativi  dalla Regione o Provincia autonoma", "values": [{"2016": {"abs": 0.0, "pc": 0.0}}, {"2017": {"abs": 0.0, "pc": 0.0}}, {"2018": {"abs": 0.0, "pc": 0.0}}]}]}, {"slug": "pcox-quadro-2-3", "label": "Trasferimenti correnti", "values": [{"2016": {"abs": 593997.47, "pc": 188.092929069031}}, {"2017": {"abs": 0.0, "pc": 0.0}}, {"2018": {"abs": 0.0, "pc": 0.0}}], "children": [{"slug": "pcox-quadro-2-3-20", "label": "Trasferimenti correnti da Amministrazioni pubbliche -", "values": [{"2016": {"abs": 311245.81, "pc": 98.5578879037365}}, {"2017": {"abs": 0.0, "pc": 0.0}}, {"2018": {"abs": 0.0, "pc": 0.0}}]}, {"slug": "pcox-quadro-2-3-22", "label": "Trasferimenti correnti da Famiglie", "values": [{"2016": {"abs": 0.0, "pc": 0.0}}, {"2017": {"abs": 0.0, "pc": 0.0}}, {"2018": {"abs": 0.0, "pc": 0.0}}]}, {"slug": "pcox-quadro-2-3-24", "label": "Trasferimenti correnti da Imprese", "values": [{"2016": {"abs": 282751.66, "pc": 89.5350411652945}}, {"2017": {"abs": 0.0, "pc": 0.0}}, {"2018": {"abs": 0.0, "pc": 0.0}}]}, {"slug": "pcox-quadro-2-3-26", "label": "Trasferimenti correnti da Istituzioni Sociali Private", "values": [{"2016": {"abs": 0.0, "pc": 0.0}}, {"2017": {"abs": 0.0, "pc": 0.0}}, {"2018": {"abs": 0.0, "pc": 0.0}}]}, {"slug": "pcox-quadro-2-3-28", "label": "Trasferimenti correnti dall'Unione europea e dal Resto del Mondo- previsione di cassa", "values": [{"2016": {"abs": 0.0, "pc": 0.0}}, {"2017": {"abs": 0.0, "pc": 0.0}}, {"2018": {"abs": 0.0, "pc": 0.0}}]}]}, {"slug": "pcox-quadro-2-4", "label": "Entrate extratributarie", "values": [{"2016": {"abs": 534254.77, "pc": 169.175037998733}}, {"2017": {"abs": 0.0, "pc": 0.0}}, {"2018": {"abs": 0.0, "pc": 0.0}}], "children": [{"slug": "pcox-quadro-2-4-32", "label": "Vendita di beni e servizi e proventi derivanti dalla gestione dei beni", "values": [{"2016": {"abs": 130184.59, "pc": 41.2237460417986}}, {"2017": {"abs": 0.0, "pc": 0.0}}, {"2018": {"abs": 0.0, "pc": 0.0}}]}, {"slug": "pcox-quadro-2-4-34", "label": "Proventi derivanti dall'attivit\u00e0 di controllo e repressione delle irregolarit\u00e0 e degli illeciti", "values": [{"2016": {"abs": 11613.83, "pc": 3.67759024699177}}, {"2017": {"abs": 0.0, "pc": 0.0}}, {"2018": {"abs": 0.0, "pc": 0.0}}]}, {"slug": "pcox-quadro-2-4-36", "label": "Interessi attivi", "values": [{"2016": {"abs": 2669.42, "pc": 0.845288157061431}}, {"2017": {"abs": 0.0, "pc": 0.0}}, {"2018": {"abs": 0.0, "pc": 0.0}}]}, {"slug": "pcox-quadro-2-4-38", "label": "Altre entrate da redditi da capitale", "values": [{"2016": {"abs": 0.0, "pc": 0.0}}, {"2017": {"abs": 0.0, "pc": 0.0}}, {"2018": {"abs": 0.0, "pc": 0.0}}]}, {"slug": "pcox-quadro-2-4-40", "label": "Rimborsi e altre entrate correnti", "values": [{"2016": {"abs": 389786.93, "pc": 123.428413552882}}, {"2017": {"abs": 0.0, "pc": 0.0}}, {"2018": {"abs": 0.0, "pc": 0.0}}]}]}, {"slug": "pcox-quadro-2-5", "label": "Entrate in conto capitale", "values": [{"2016": {"abs": 3549439.26, "pc": 1123.95163394554}}, {"2017": {"abs": 0.0, "pc": 0.0}}, {"2018": {"abs": 0.0, "pc": 0.0}}], "children": [{"slug": "pcox-quadro-2-5-44", "label": "Tributi in conto capitale", "values": [{"2016": {"abs": 0.0, "pc": 0.0}}, {"2017": {"abs": 0.0, "pc": 0.0}}, {"2018": {"abs": 0.0, "pc": 0.0}}]}, {"slug": "pcox-quadro-2-5-46", "label": "Contributi agli investimenti", "values": [{"2016": {"abs": 3390034.26, "pc": 1073.47506649778}}, {"2017": {"abs": 0.0, "pc": 0.0}}, {"2018": {"abs": 0.0, "pc": 0.0}}]}, {"slug": "pcox-quadro-2-5-48", "label": "Altri trasferimenti in conto capitale", "values": [{"2016": {"abs": 0.0, "pc": 0.0}}, {"2017": {"abs": 0.0, "pc": 0.0}}, {"2018": {"abs": 0.0, "pc": 0.0}}]}, {"slug": "pcox-quadro-2-5-50", "label": "Entrate da alienazione di beni materiali e immateriali", "values": [{"2016": {"abs": 99405.0, "pc": 31.4772007599747}}, {"2017": {"abs": 0.0, "pc": 0.0}}, {"2018": {"abs": 0.0, "pc": 0.0}}]}, {"slug": "pcox-quadro-2-5-52", "label": "Altre entrate in conto capitale", "values": [{"2016": {"abs": 60000.0, "pc": 18.9993666877771}}, {"2017": {"abs": 0.0, "pc": 0.0}}, {"2018": {"abs": 0.0, "pc": 0.0}}]}]}, {"slug": "pcox-quadro-2-6", "label": "Entrate da riduzione di attivita\u0300 finanziarie", "values": [{"2016": {"abs": 0.0, "pc": 0.0}}, {"2017": {"abs": 0.0, "pc": 0.0}}, {"2018": {"abs": 0.0, "pc": 0.0}}], "children": [{"slug": "pcox-quadro-2-6-56", "label": "Alienazione di attivit\u00e0 finanziarie", "values": [{"2016": {"abs": 0.0, "pc": 0.0}}, {"2017": {"abs": 0.0, "pc": 0.0}}, {"2018": {"abs": 0.0, "pc": 0.0}}]}, {"slug": "pcox-quadro-2-6-58", "label": "Riscossione crediti di breve termine", "values": [{"2016": {"abs": 0.0, "pc": 0.0}}, {"2017": {"abs": 0.0, "pc": 0.0}}, {"2018": {"abs": 0.0, "pc": 0.0}}]}, {"slug": "pcox-quadro-2-6-60", "label": "Riscossione crediti di medio", "values": [{"2016": {"abs": 0.0, "pc": 0.0}}, {"2017": {"abs": 0.0, "pc": 0.0}}, {"2018": {"abs": 0.0, "pc": 0.0}}]}, {"slug": "pcox-quadro-2-6-62", "label": "Altre entrate per riduzione di attivit\u00e0 finanziarie", "values": [{"2016": {"abs": 0.0, "pc": 0.0}}, {"2017": {"abs": 0.0, "pc": 0.0}}, {"2018": {"abs": 0.0, "pc": 0.0}}]}]}, {"slug": "pcox-quadro-2-7", "label": "Accensione prestiti", "values": [{"2016": {"abs": 584065.78, "pc": 184.947998733376}}, {"2017": {"abs": 0.0, "pc": 0.0}}, {"2018": {"abs": 0.0, "pc": 0.0}}], "children": [{"slug": "pcox-quadro-2-7-66", "label": "Emissione di titoli obbligazionari", "values": [{"2016": {"abs": 0.0, "pc": 0.0}}, {"2017": {"abs": 0.0, "pc": 0.0}}, {"2018": {"abs": 0.0, "pc": 0.0}}]}, {"slug": "pcox-quadro-2-7-68", "label": "Accensione prestiti a breve termine", "values": [{"2016": {"abs": 0.0, "pc": 0.0}}, {"2017": {"abs": 0.0, "pc": 0.0}}, {"2018": {"abs": 0.0, "pc": 0.0}}]}, {"slug": "pcox-quadro-2-7-70", "label": "Accensione mutui e altri finanziamenti a medio lungo termine", "values": [{"2016": {"abs": 584065.78, "pc": 184.947998733376}}, {"2017": {"abs": 0.0, "pc": 0.0}}, {"2018": {"abs": 0.0, "pc": 0.0}}]}, {"slug": "pcox-quadro-2-7-72", "label": "Altre forme di indebitamento", "values": [{"2016": {"abs": 0.0, "pc": 0.0}}, {"2017": {"abs": 0.0, "pc": 0.0}}, {"2018": {"abs": 0.0, "pc": 0.0}}]}]}, {"slug": "pcox-quadro-2-8", "label": "Anticipazioni da istituto tesoriere/cassiere", "values": [{"2016": {"abs": 516463.0, "pc": 163.54116529449}}, {"2017": {"abs": 0.0, "pc": 0.0}}, {"2018": {"abs": 0.0, "pc": 0.0}}], "children": [{"slug": "pcox-quadro-2-8-76", "label": "Anticipazione da istituto tesoriere/cassiere", "values": [{"2016": {"abs": 516463.0, "pc": 163.54116529449}}, {"2017": {"abs": 0.0, "pc": 0.0}}, {"2018": {"abs": 0.0, "pc": 0.0}}]}]}, {"slug": "pcox-quadro-2-9", "label": "Entrate per conto terzi e partite di giro", "values": [{"2016": {"abs": 1086189.63, "pc": 343.948584547182}}, {"2017": {"abs": 0.0, "pc": 0.0}}, {"2018": {"abs": 0.0, "pc": 0.0}}], "children": [{"slug": "pcox-quadro-2-9-80", "label": "Entrate per partite di giro", "values": [{"2016": {"abs": 720535.43, "pc": 228.161947435086}}, {"2017": {"abs": 0.0, "pc": 0.0}}, {"2018": {"abs": 0.0, "pc": 0.0}}]}, {"slug": "pcox-quadro-2-9-82", "label": "Entrate per conto terzi", "values": [{"2016": {"abs": 365654.2, "pc": 115.786637112096}}, {"2017": {"abs": 0.0, "pc": 0.0}}, {"2018": {"abs": 0.0, "pc": 0.0}}]}]}]