[{"slug": "pcox-quadro-2-11", "label": "Totale generale delle Entrate", "values": [{"2016": {"abs": 172422691.13, "pc": 2136.74735581332}}, {"2017": {"abs": 0.0, "pc": 0.0}}, {"2018": {"abs": 0.0, "pc": 0.0}}], "children": []}, {"slug": "pcox-quadro-2-2", "label": "Entrate correnti di natura tributaria, contributiva e perequativa", "values": [{"2016": {"abs": 66629988.62, "pc": 825.711807817186}}, {"2017": {"abs": 0.0, "pc": 0.0}}, {"2018": {"abs": 0.0, "pc": 0.0}}], "children": [{"slug": "pcox-quadro-2-2-10", "label": "Imposte,tasse e proventi assimilati", "values": [{"2016": {"abs": 61039829.23, "pc": 756.43578494064}}, {"2017": {"abs": 0.0, "pc": 0.0}}, {"2018": {"abs": 0.0, "pc": 0.0}}]}, {"slug": "pcox-quadro-2-2-12", "label": "Compartecipazioni di tributi", "values": [{"2016": {"abs": 9000.0, "pc": 0.11153245594468}}, {"2017": {"abs": 0.0, "pc": 0.0}}, {"2018": {"abs": 0.0, "pc": 0.0}}]}, {"slug": "pcox-quadro-2-2-14", "label": "Fondi perequativi  da Amministrazioni Centrali", "values": [{"2016": {"abs": 5581159.39, "pc": 69.1644904206013}}, {"2017": {"abs": 0.0, "pc": 0.0}}, {"2018": {"abs": 0.0, "pc": 0.0}}]}, {"slug": "pcox-quadro-2-2-16", "label": "Fondi perequativi  dalla Regione o Provincia autonoma", "values": [{"2016": {"abs": 0.0, "pc": 0.0}}, {"2017": {"abs": 0.0, "pc": 0.0}}, {"2018": {"abs": 0.0, "pc": 0.0}}]}]}, {"slug": "pcox-quadro-2-3", "label": "Trasferimenti correnti", "values": [{"2016": {"abs": 10746939.83, "pc": 133.181399236622}}, {"2017": {"abs": 0.0, "pc": 0.0}}, {"2018": {"abs": 0.0, "pc": 0.0}}], "children": [{"slug": "pcox-quadro-2-3-20", "label": "Trasferimenti correnti da Amministrazioni pubbliche -", "values": [{"2016": {"abs": 10487210.83, "pc": 129.962708875505}}, {"2017": {"abs": 0.0, "pc": 0.0}}, {"2018": {"abs": 0.0, "pc": 0.0}}]}, {"slug": "pcox-quadro-2-3-22", "label": "Trasferimenti correnti da Famiglie", "values": [{"2016": {"abs": 13750.0, "pc": 0.170396807693261}}, {"2017": {"abs": 0.0, "pc": 0.0}}, {"2018": {"abs": 0.0, "pc": 0.0}}]}, {"slug": "pcox-quadro-2-3-24", "label": "Trasferimenti correnti da Imprese", "values": [{"2016": {"abs": 245979.0, "pc": 3.04829355342405}}, {"2017": {"abs": 0.0, "pc": 0.0}}, {"2018": {"abs": 0.0, "pc": 0.0}}]}, {"slug": "pcox-quadro-2-3-26", "label": "Trasferimenti correnti da Istituzioni Sociali Private", "values": [{"2016": {"abs": 0.0, "pc": 0.0}}, {"2017": {"abs": 0.0, "pc": 0.0}}, {"2018": {"abs": 0.0, "pc": 0.0}}]}, {"slug": "pcox-quadro-2-3-28", "label": "Trasferimenti correnti dall'Unione europea e dal Resto del Mondo- previsione di cassa", "values": [{"2016": {"abs": 0.0, "pc": 0.0}}, {"2017": {"abs": 0.0, "pc": 0.0}}, {"2018": {"abs": 0.0, "pc": 0.0}}]}]}, {"slug": "pcox-quadro-2-4", "label": "Entrate extratributarie", "values": [{"2016": {"abs": 30357031.83, "pc": 376.199368354524}}, {"2017": {"abs": 0.0, "pc": 0.0}}, {"2018": {"abs": 0.0, "pc": 0.0}}], "children": [{"slug": "pcox-quadro-2-4-32", "label": "Vendita di beni e servizi e proventi derivanti dalla gestione dei beni", "values": [{"2016": {"abs": 16264425.45, "pc": 201.556812774184}}, {"2017": {"abs": 0.0, "pc": 0.0}}, {"2018": {"abs": 0.0, "pc": 0.0}}]}, {"slug": "pcox-quadro-2-4-34", "label": "Proventi derivanti dall'attivit\u00e0 di controllo e repressione delle irregolarit\u00e0 e degli illeciti", "values": [{"2016": {"abs": 7207329.44, "pc": 89.3167948050661}}, {"2017": {"abs": 0.0, "pc": 0.0}}, {"2018": {"abs": 0.0, "pc": 0.0}}]}, {"slug": "pcox-quadro-2-4-36", "label": "Interessi attivi", "values": [{"2016": {"abs": 474210.9, "pc": 5.87665625697078}}, {"2017": {"abs": 0.0, "pc": 0.0}}, {"2018": {"abs": 0.0, "pc": 0.0}}]}, {"slug": "pcox-quadro-2-4-38", "label": "Altre entrate da redditi da capitale", "values": [{"2016": {"abs": 4001459.0, "pc": 49.5880610702159}}, {"2017": {"abs": 0.0, "pc": 0.0}}, {"2018": {"abs": 0.0, "pc": 0.0}}]}, {"slug": "pcox-quadro-2-4-40", "label": "Rimborsi e altre entrate correnti", "values": [{"2016": {"abs": 2409607.04, "pc": 29.8610434480878}}, {"2017": {"abs": 0.0, "pc": 0.0}}, {"2018": {"abs": 0.0, "pc": 0.0}}]}]}, {"slug": "pcox-quadro-2-5", "label": "Entrate in conto capitale", "values": [{"2016": {"abs": 22657643.01, "pc": 280.784730091457}}, {"2017": {"abs": 0.0, "pc": 0.0}}, {"2018": {"abs": 0.0, "pc": 0.0}}], "children": [{"slug": "pcox-quadro-2-5-44", "label": "Tributi in conto capitale", "values": [{"2016": {"abs": 206000.0, "pc": 2.55285399162267}}, {"2017": {"abs": 0.0, "pc": 0.0}}, {"2018": {"abs": 0.0, "pc": 0.0}}]}, {"slug": "pcox-quadro-2-5-46", "label": "Contributi agli investimenti", "values": [{"2016": {"abs": 16657817.04, "pc": 206.431916127593}}, {"2017": {"abs": 0.0, "pc": 0.0}}, {"2018": {"abs": 0.0, "pc": 0.0}}]}, {"slug": "pcox-quadro-2-5-48", "label": "Altri trasferimenti in conto capitale", "values": [{"2016": {"abs": 311525.98, "pc": 3.86058418221925}}, {"2017": {"abs": 0.0, "pc": 0.0}}, {"2018": {"abs": 0.0, "pc": 0.0}}]}, {"slug": "pcox-quadro-2-5-50", "label": "Entrate da alienazione di beni materiali e immateriali", "values": [{"2016": {"abs": 2669215.25, "pc": 33.0782369197214}}, {"2017": {"abs": 0.0, "pc": 0.0}}, {"2018": {"abs": 0.0, "pc": 0.0}}]}, {"slug": "pcox-quadro-2-5-52", "label": "Altre entrate in conto capitale", "values": [{"2016": {"abs": 2813084.74, "pc": 34.8611388703002}}, {"2017": {"abs": 0.0, "pc": 0.0}}, {"2018": {"abs": 0.0, "pc": 0.0}}]}]}, {"slug": "pcox-quadro-2-6", "label": "Entrate da riduzione di attivita\u0300 finanziarie", "values": [{"2016": {"abs": 8741583.1, "pc": 108.33002577639}}, {"2017": {"abs": 0.0, "pc": 0.0}}, {"2018": {"abs": 0.0, "pc": 0.0}}], "children": [{"slug": "pcox-quadro-2-6-56", "label": "Alienazione di attivit\u00e0 finanziarie", "values": [{"2016": {"abs": 6485889.94, "pc": 80.3763593327881}}, {"2017": {"abs": 0.0, "pc": 0.0}}, {"2018": {"abs": 0.0, "pc": 0.0}}]}, {"slug": "pcox-quadro-2-6-58", "label": "Riscossione crediti di breve termine", "values": [{"2016": {"abs": 0.0, "pc": 0.0}}, {"2017": {"abs": 0.0, "pc": 0.0}}, {"2018": {"abs": 0.0, "pc": 0.0}}]}, {"slug": "pcox-quadro-2-6-60", "label": "Riscossione crediti di medio", "values": [{"2016": {"abs": 2255693.16, "pc": 27.9536664436018}}, {"2017": {"abs": 0.0, "pc": 0.0}}, {"2018": {"abs": 0.0, "pc": 0.0}}]}, {"slug": "pcox-quadro-2-6-62", "label": "Altre entrate per riduzione di attivit\u00e0 finanziarie", "values": [{"2016": {"abs": 0.0, "pc": 0.0}}, {"2017": {"abs": 0.0, "pc": 0.0}}, {"2018": {"abs": 0.0, "pc": 0.0}}]}]}, {"slug": "pcox-quadro-2-7", "label": "Accensione prestiti", "values": [{"2016": {"abs": 3507935.74, "pc": 43.4720764864798}}, {"2017": {"abs": 0.0, "pc": 0.0}}, {"2018": {"abs": 0.0, "pc": 0.0}}], "children": [{"slug": "pcox-quadro-2-7-66", "label": "Emissione di titoli obbligazionari", "values": [{"2016": {"abs": 0.0, "pc": 0.0}}, {"2017": {"abs": 0.0, "pc": 0.0}}, {"2018": {"abs": 0.0, "pc": 0.0}}]}, {"slug": "pcox-quadro-2-7-68", "label": "Accensione prestiti a breve termine", "values": [{"2016": {"abs": 0.0, "pc": 0.0}}, {"2017": {"abs": 0.0, "pc": 0.0}}, {"2018": {"abs": 0.0, "pc": 0.0}}]}, {"slug": "pcox-quadro-2-7-70", "label": "Accensione mutui e altri finanziamenti a medio lungo termine", "values": [{"2016": {"abs": 1078155.69, "pc": 13.3610391107146}}, {"2017": {"abs": 0.0, "pc": 0.0}}, {"2018": {"abs": 0.0, "pc": 0.0}}]}, {"slug": "pcox-quadro-2-7-72", "label": "Altre forme di indebitamento", "values": [{"2016": {"abs": 2429780.05, "pc": 30.1110373757652}}, {"2017": {"abs": 0.0, "pc": 0.0}}, {"2018": {"abs": 0.0, "pc": 0.0}}]}]}, {"slug": "pcox-quadro-2-8", "label": "Anticipazioni da istituto tesoriere/cassiere", "values": [{"2016": {"abs": 5164569.0, "pc": 64.0018960517511}}, {"2017": {"abs": 0.0, "pc": 0.0}}, {"2018": {"abs": 0.0, "pc": 0.0}}], "children": [{"slug": "pcox-quadro-2-8-76", "label": "Anticipazione da istituto tesoriere/cassiere", "values": [{"2016": {"abs": 5164569.0, "pc": 64.0018960517511}}, {"2017": {"abs": 0.0, "pc": 0.0}}, {"2018": {"abs": 0.0, "pc": 0.0}}]}]}, {"slug": "pcox-quadro-2-9", "label": "Entrate per conto terzi e partite di giro", "values": [{"2016": {"abs": 24617000.0, "pc": 305.066051998909}}, {"2017": {"abs": 0.0, "pc": 0.0}}, {"2018": {"abs": 0.0, "pc": 0.0}}], "children": [{"slug": "pcox-quadro-2-9-80", "label": "Entrate per partite di giro", "values": [{"2016": {"abs": 17440000.0, "pc": 216.12511463058}}, {"2017": {"abs": 0.0, "pc": 0.0}}, {"2018": {"abs": 0.0, "pc": 0.0}}]}, {"slug": "pcox-quadro-2-9-82", "label": "Entrate per conto terzi", "values": [{"2016": {"abs": 7177000.0, "pc": 88.9409373683297}}, {"2017": {"abs": 0.0, "pc": 0.0}}, {"2018": {"abs": 0.0, "pc": 0.0}}]}]}]